idutils/__init__.py
inspire_idutils-1.2.5.dist-info/AUTHORS.rst
inspire_idutils-1.2.5.dist-info/LICENSE
inspire_idutils-1.2.5.dist-info/METADATA
inspire_idutils-1.2.5.dist-info/WHEEL
inspire_idutils-1.2.5.dist-info/top_level.txt
inspire_idutils-1.2.5.dist-info/RECORD
