Metadata-Version: 2.1
Name: inspire-idutils
Version: 1.2.5
Summary: "Small library for persistent identifiers used in scholarly communication."
Home-page: https://github.com/inveniosoftware/idutils
Author: Invenio Software
Author-email: info@inveniosoftware.org
License: Revised BSD License
Keywords: persistent identifiers
Platform: any
Classifier: Development Status :: 5 - Production/Stable
Requires-Python: >=2.7
License-File: LICENSE
License-File: AUTHORS.rst
Requires-Dist: six >=1.10
Requires-Dist: isbnlib >=3.10.8
Provides-Extra: docs
Provides-Extra: tests
Requires-Dist: pytest-black-ng >=0.4.0 ; extra == 'tests'
Requires-Dist: pytest-cache >=1.0 ; extra == 'tests'
Requires-Dist: pytest-runner >=2.6.2 ; extra == 'tests'
Requires-Dist: pytest-invenio >=1.4.0 ; extra == 'tests'
Requires-Dist: sphinx >=4.5 ; extra == 'tests'
